MANIFEST.in
README.md
requirements.txt
setup.cfg
setup.py
tellsticknet/__init__.py
tellsticknet/__main__.py
tellsticknet/const.py
tellsticknet/controller.py
tellsticknet/discovery.py
tellsticknet/mqtt.py
tellsticknet/protocol.py
tellsticknet/test_protocols.py
tellsticknet/util.py
tellsticknet.egg-info/PKG-INFO
tellsticknet.egg-info/SOURCES.txt
tellsticknet.egg-info/dependency_links.txt
tellsticknet.egg-info/entry_points.txt
tellsticknet.egg-info/not-zip-safe
tellsticknet.egg-info/requires.txt
tellsticknet.egg-info/top_level.txt
tellsticknet/protocols/__init__.py
tellsticknet/protocols/arctech.py
tellsticknet/protocols/everflourish.py
tellsticknet/protocols/fineoffset.py
tellsticknet/protocols/mandolyn.py
tellsticknet/protocols/nexa.py
tellsticknet/protocols/oregon.py
tellsticknet/protocols/sartano.py
tellsticknet/protocols/waveman.py