Metadata-Version: 1.0
Name: tellsticknet
Version: 0.1.2
Summary: Listen for UDP sensor broadcasts from a Tellstick
Home-page: https://github.com/molobrakos/tellsticknet
Author: Erik Eriksson
Author-email: error.errorsson@gmail.com
License: ?
Keywords: tellstick
Platform: UNKNOWN
